{
  "id": "c0d6b8e6-560a-41b2-8bac-fbc79af8f16b",
  "prevId": "a9f500cf-d7eb-43dd-9597-13b26197d3af",
  "version": "7",
  "dialect": "postgresql",
  "tables": {
    "public.activity_logs": {
      "name": "activity_logs",
      "schema": "",
      "columns": {
        "id": {
          "name": "id",
          "type": "text",
          "primaryKey": true,
          "notNull": true
        },
        "workshop_id": {
          "name": "workshop_id",
          "type": "text",
          "primaryKey": false,
          "notNull": true
        },
        "tenant_id": {
          "name": "tenant_id",
          "type": "text",
          "primaryKey": false,
          "notNull": true
        },
        "actor_name": {
          "name": "actor_name",
          "type": "text",
          "primaryKey": false,
          "notNull": true
        },
        "action": {
          "name": "action",
          "type": "text",
          "primaryKey": false,
          "notNull": true
        },
        "details": {
          "name": "details",
          "type": "text",
          "primaryKey": false,
          "notNull": false
        },
        "created_at": {
          "name": "created_at",
          "type": "timestamp",
          "primaryKey": false,
          "notNull": true,
          "default": "now()"
        }
      },
      "indexes": {},
      "foreignKeys": {},
      "compositePrimaryKeys": {},
      "uniqueConstraints": {},
      "policies": {},
      "checkConstraints": {},
      "isRLSEnabled": false
    },
    "public.artifacts": {
      "name": "artifacts",
      "schema": "",
      "columns": {
        "id": {
          "name": "id",
          "type": "text",
          "primaryKey": true,
          "notNull": true
        },
        "workshop_id": {
          "name": "workshop_id",
          "type": "text",
          "primaryKey": false,
          "notNull": true
        },
        "tenant_id": {
          "name": "tenant_id",
          "type": "text",
          "primaryKey": false,
          "notNull": true
        },
        "uploaded_by": {
          "name": "uploaded_by",
          "type": "text",
          "primaryKey": false,
          "notNull": true
        },
        "type": {
          "name": "type",
          "type": "text",
          "primaryKey": false,
          "notNull": true,
          "default": "'document'"
        },
        "title": {
          "name": "title",
          "type": "text",
          "primaryKey": false,
          "notNull": true
        },
        "storage_url": {
          "name": "storage_url",
          "type": "text",
          "primaryKey": false,
          "notNull": true
        },
        "visibility": {
          "name": "visibility",
          "type": "text",
          "primaryKey": false,
          "notNull": true,
          "default": "'all'"
        },
        "created_at": {
          "name": "created_at",
          "type": "timestamp",
          "primaryKey": false,
          "notNull": true,
          "default": "now()"
        }
      },
      "indexes": {},
      "foreignKeys": {},
      "compositePrimaryKeys": {},
      "uniqueConstraints": {},
      "policies": {},
      "checkConstraints": {},
      "isRLSEnabled": false
    },
    "public.contributor_inputs": {
      "name": "contributor_inputs",
      "schema": "",
      "columns": {
        "id": {
          "name": "id",
          "type": "text",
          "primaryKey": true,
          "notNull": true
        },
        "workshop_id": {
          "name": "workshop_id",
          "type": "text",
          "primaryKey": false,
          "notNull": true
        },
        "participant_id": {
          "name": "participant_id",
          "type": "text",
          "primaryKey": false,
          "notNull": true
        },
        "tenant_id": {
          "name": "tenant_id",
          "type": "text",
          "primaryKey": false,
          "notNull": true
        },
        "goals_and_objectives": {
          "name": "goals_and_objectives",
          "type": "text",
          "primaryKey": false,
          "notNull": false
        },
        "pain_points": {
          "name": "pain_points",
          "type": "text",
          "primaryKey": false,
          "notNull": false
        },
        "current_workflow": {
          "name": "current_workflow",
          "type": "text",
          "primaryKey": false,
          "notNull": false
        },
        "constraints": {
          "name": "constraints",
          "type": "text",
          "primaryKey": false,
          "notNull": false
        },
        "success_criteria": {
          "name": "success_criteria",
          "type": "text",
          "primaryKey": false,
          "notNull": false
        },
        "completion_pct": {
          "name": "completion_pct",
          "type": "integer",
          "primaryKey": false,
          "notNull": true,
          "default": 0
        },
        "status": {
          "name": "status",
          "type": "text",
          "primaryKey": false,
          "notNull": true,
          "default": "'pending'"
        },
        "submitted_at": {
          "name": "submitted_at",
          "type": "timestamp",
          "primaryKey": false,
          "notNull": false
        }
      },
      "indexes": {},
      "foreignKeys": {},
      "compositePrimaryKeys": {},
      "uniqueConstraints": {},
      "policies": {},
      "checkConstraints": {},
      "isRLSEnabled": false
    },
    "public.insights": {
      "name": "insights",
      "schema": "",
      "columns": {
        "id": {
          "name": "id",
          "type": "text",
          "primaryKey": true,
          "notNull": true
        },
        "workshop_id": {
          "name": "workshop_id",
          "type": "text",
          "primaryKey": false,
          "notNull": true
        },
        "use_case_id": {
          "name": "use_case_id",
          "type": "text",
          "primaryKey": false,
          "notNull": true
        },
        "team_id": {
          "name": "team_id",
          "type": "text",
          "primaryKey": false,
          "notNull": true
        },
        "title": {
          "name": "title",
          "type": "text",
          "primaryKey": false,
          "notNull": true
        },
        "summary": {
          "name": "summary",
          "type": "text",
          "primaryKey": false,
          "notNull": true
        },
        "value": {
          "name": "value",
          "type": "text",
          "primaryKey": false,
          "notNull": true
        },
        "viability": {
          "name": "viability",
          "type": "text",
          "primaryKey": false,
          "notNull": true
        },
        "visibility": {
          "name": "visibility",
          "type": "text",
          "primaryKey": false,
          "notNull": true
        },
        "added_by": {
          "name": "added_by",
          "type": "text",
          "primaryKey": false,
          "notNull": true
        },
        "upvotes": {
          "name": "upvotes",
          "type": "integer",
          "primaryKey": false,
          "notNull": true,
          "default": 0
        },
        "tags": {
          "name": "tags",
          "type": "jsonb",
          "primaryKey": false,
          "notNull": true,
          "default": "'[]'"
        },
        "created_at": {
          "name": "created_at",
          "type": "timestamp",
          "primaryKey": false,
          "notNull": true,
          "default": "now()"
        }
      },
      "indexes": {},
      "foreignKeys": {
        "insights_workshop_id_workshops_id_fk": {
          "name": "insights_workshop_id_workshops_id_fk",
          "tableFrom": "insights",
          "tableTo": "workshops",
          "columnsFrom": [
            "workshop_id"
          ],
          "columnsTo": [
            "id"
          ],
          "onDelete": "no action",
          "onUpdate": "no action"
        },
        "insights_use_case_id_use_cases_id_fk": {
          "name": "insights_use_case_id_use_cases_id_fk",
          "tableFrom": "insights",
          "tableTo": "use_cases",
          "columnsFrom": [
            "use_case_id"
          ],
          "columnsTo": [
            "id"
          ],
          "onDelete": "no action",
          "onUpdate": "no action"
        },
        "insights_team_id_teams_id_fk": {
          "name": "insights_team_id_teams_id_fk",
          "tableFrom": "insights",
          "tableTo": "teams",
          "columnsFrom": [
            "team_id"
          ],
          "columnsTo": [
            "id"
          ],
          "onDelete": "no action",
          "onUpdate": "no action"
        }
      },
      "compositePrimaryKeys": {},
      "uniqueConstraints": {},
      "policies": {},
      "checkConstraints": {},
      "isRLSEnabled": false
    },
    "public.participants": {
      "name": "participants",
      "schema": "",
      "columns": {
        "id": {
          "name": "id",
          "type": "text",
          "primaryKey": true,
          "notNull": true
        },
        "workshop_id": {
          "name": "workshop_id",
          "type": "text",
          "primaryKey": false,
          "notNull": true
        },
        "name": {
          "name": "name",
          "type": "text",
          "primaryKey": false,
          "notNull": true
        },
        "role": {
          "name": "role",
          "type": "text",
          "primaryKey": false,
          "notNull": true
        },
        "presence": {
          "name": "presence",
          "type": "text",
          "primaryKey": false,
          "notNull": true,
          "default": "'remote'"
        },
        "team_id": {
          "name": "team_id",
          "type": "text",
          "primaryKey": false,
          "notNull": false
        },
        "initials": {
          "name": "initials",
          "type": "text",
          "primaryKey": false,
          "notNull": true
        },
        "color": {
          "name": "color",
          "type": "text",
          "primaryKey": false,
          "notNull": true
        },
        "created_at": {
          "name": "created_at",
          "type": "timestamp",
          "primaryKey": false,
          "notNull": true,
          "default": "now()"
        }
      },
      "indexes": {},
      "foreignKeys": {
        "participants_workshop_id_workshops_id_fk": {
          "name": "participants_workshop_id_workshops_id_fk",
          "tableFrom": "participants",
          "tableTo": "workshops",
          "columnsFrom": [
            "workshop_id"
          ],
          "columnsTo": [
            "id"
          ],
          "onDelete": "no action",
          "onUpdate": "no action"
        }
      },
      "compositePrimaryKeys": {},
      "uniqueConstraints": {},
      "policies": {},
      "checkConstraints": {},
      "isRLSEnabled": false
    },
    "public.pre_participants": {
      "name": "pre_participants",
      "schema": "",
      "columns": {
        "id": {
          "name": "id",
          "type": "text",
          "primaryKey": true,
          "notNull": true
        },
        "workshop_id": {
          "name": "workshop_id",
          "type": "text",
          "primaryKey": false,
          "notNull": true
        },
        "tenant_id": {
          "name": "tenant_id",
          "type": "text",
          "primaryKey": false,
          "notNull": true
        },
        "name": {
          "name": "name",
          "type": "text",
          "primaryKey": false,
          "notNull": true
        },
        "email": {
          "name": "email",
          "type": "text",
          "primaryKey": false,
          "notNull": false
        },
        "role": {
          "name": "role",
          "type": "text",
          "primaryKey": false,
          "notNull": true,
          "default": "'contributor'"
        },
        "status": {
          "name": "status",
          "type": "text",
          "primaryKey": false,
          "notNull": true,
          "default": "'pending'"
        },
        "created_at": {
          "name": "created_at",
          "type": "timestamp",
          "primaryKey": false,
          "notNull": true,
          "default": "now()"
        }
      },
      "indexes": {},
      "foreignKeys": {},
      "compositePrimaryKeys": {},
      "uniqueConstraints": {},
      "policies": {},
      "checkConstraints": {},
      "isRLSEnabled": false
    },
    "public.pre_workshops": {
      "name": "pre_workshops",
      "schema": "",
      "columns": {
        "id": {
          "name": "id",
          "type": "text",
          "primaryKey": true,
          "notNull": true
        },
        "tenant_id": {
          "name": "tenant_id",
          "type": "text",
          "primaryKey": false,
          "notNull": true
        },
        "title": {
          "name": "title",
          "type": "text",
          "primaryKey": false,
          "notNull": true
        },
        "focus_area": {
          "name": "focus_area",
          "type": "text",
          "primaryKey": false,
          "notNull": false
        },
        "objective": {
          "name": "objective",
          "type": "text",
          "primaryKey": false,
          "notNull": false
        },
        "status": {
          "name": "status",
          "type": "text",
          "primaryKey": false,
          "notNull": true,
          "default": "'draft'"
        },
        "data_sensitivity": {
          "name": "data_sensitivity",
          "type": "text",
          "primaryKey": false,
          "notNull": true,
          "default": "'internal'"
        },
        "lead_facilitator_name": {
          "name": "lead_facilitator_name",
          "type": "text",
          "primaryKey": false,
          "notNull": false
        },
        "ai_context": {
          "name": "ai_context",
          "type": "text",
          "primaryKey": false,
          "notNull": false
        },
        "kickoff_summary": {
          "name": "kickoff_summary",
          "type": "text",
          "primaryKey": false,
          "notNull": false
        },
        "facilitator_code": {
          "name": "facilitator_code",
          "type": "text",
          "primaryKey": false,
          "notNull": false
        },
        "contributor_code": {
          "name": "contributor_code",
          "type": "text",
          "primaryKey": false,
          "notNull": false
        },
        "created_at": {
          "name": "created_at",
          "type": "timestamp",
          "primaryKey": false,
          "notNull": true,
          "default": "now()"
        },
        "updated_at": {
          "name": "updated_at",
          "type": "timestamp",
          "primaryKey": false,
          "notNull": true,
          "default": "now()"
        }
      },
      "indexes": {},
      "foreignKeys": {},
      "compositePrimaryKeys": {},
      "uniqueConstraints": {},
      "policies": {},
      "checkConstraints": {},
      "isRLSEnabled": false
    },
    "public.promotions": {
      "name": "promotions",
      "schema": "",
      "columns": {
        "id": {
          "name": "id",
          "type": "text",
          "primaryKey": true,
          "notNull": true
        },
        "workshop_id": {
          "name": "workshop_id",
          "type": "text",
          "primaryKey": false,
          "notNull": true
        },
        "use_case_id": {
          "name": "use_case_id",
          "type": "text",
          "primaryKey": false,
          "notNull": true
        },
        "promoted_by": {
          "name": "promoted_by",
          "type": "text",
          "primaryKey": false,
          "notNull": true
        },
        "target_type": {
          "name": "target_type",
          "type": "text",
          "primaryKey": false,
          "notNull": true
        },
        "promoted_at": {
          "name": "promoted_at",
          "type": "timestamp",
          "primaryKey": false,
          "notNull": true,
          "default": "now()"
        }
      },
      "indexes": {},
      "foreignKeys": {
        "promotions_workshop_id_workshops_id_fk": {
          "name": "promotions_workshop_id_workshops_id_fk",
          "tableFrom": "promotions",
          "tableTo": "workshops",
          "columnsFrom": [
            "workshop_id"
          ],
          "columnsTo": [
            "id"
          ],
          "onDelete": "no action",
          "onUpdate": "no action"
        },
        "promotions_use_case_id_use_cases_id_fk": {
          "name": "promotions_use_case_id_use_cases_id_fk",
          "tableFrom": "promotions",
          "tableTo": "use_cases",
          "columnsFrom": [
            "use_case_id"
          ],
          "columnsTo": [
            "id"
          ],
          "onDelete": "no action",
          "onUpdate": "no action"
        }
      },
      "compositePrimaryKeys": {},
      "uniqueConstraints": {},
      "policies": {},
      "checkConstraints": {},
      "isRLSEnabled": false
    },
    "public.scores": {
      "name": "scores",
      "schema": "",
      "columns": {
        "id": {
          "name": "id",
          "type": "text",
          "primaryKey": true,
          "notNull": true
        },
        "workshop_id": {
          "name": "workshop_id",
          "type": "text",
          "primaryKey": false,
          "notNull": true
        },
        "use_case_id": {
          "name": "use_case_id",
          "type": "text",
          "primaryKey": false,
          "notNull": true
        },
        "scored_by": {
          "name": "scored_by",
          "type": "text",
          "primaryKey": false,
          "notNull": true
        },
        "impact": {
          "name": "impact",
          "type": "integer",
          "primaryKey": false,
          "notNull": true
        },
        "feasibility": {
          "name": "feasibility",
          "type": "integer",
          "primaryKey": false,
          "notNull": true
        },
        "alignment": {
          "name": "alignment",
          "type": "integer",
          "primaryKey": false,
          "notNull": true
        },
        "executive_weight": {
          "name": "executive_weight",
          "type": "integer",
          "primaryKey": false,
          "notNull": true
        },
        "notes": {
          "name": "notes",
          "type": "text",
          "primaryKey": false,
          "notNull": false
        },
        "created_at": {
          "name": "created_at",
          "type": "timestamp",
          "primaryKey": false,
          "notNull": true,
          "default": "now()"
        }
      },
      "indexes": {},
      "foreignKeys": {
        "scores_workshop_id_workshops_id_fk": {
          "name": "scores_workshop_id_workshops_id_fk",
          "tableFrom": "scores",
          "tableTo": "workshops",
          "columnsFrom": [
            "workshop_id"
          ],
          "columnsTo": [
            "id"
          ],
          "onDelete": "no action",
          "onUpdate": "no action"
        },
        "scores_use_case_id_use_cases_id_fk": {
          "name": "scores_use_case_id_use_cases_id_fk",
          "tableFrom": "scores",
          "tableTo": "use_cases",
          "columnsFrom": [
            "use_case_id"
          ],
          "columnsTo": [
            "id"
          ],
          "onDelete": "no action",
          "onUpdate": "no action"
        }
      },
      "compositePrimaryKeys": {},
      "uniqueConstraints": {},
      "policies": {},
      "checkConstraints": {},
      "isRLSEnabled": false
    },
    "public.teams": {
      "name": "teams",
      "schema": "",
      "columns": {
        "id": {
          "name": "id",
          "type": "text",
          "primaryKey": true,
          "notNull": true
        },
        "workshop_id": {
          "name": "workshop_id",
          "type": "text",
          "primaryKey": false,
          "notNull": true
        },
        "name": {
          "name": "name",
          "type": "text",
          "primaryKey": false,
          "notNull": true
        },
        "member_ids": {
          "name": "member_ids",
          "type": "jsonb",
          "primaryKey": false,
          "notNull": true,
          "default": "'[]'"
        },
        "created_at": {
          "name": "created_at",
          "type": "timestamp",
          "primaryKey": false,
          "notNull": true,
          "default": "now()"
        }
      },
      "indexes": {},
      "foreignKeys": {
        "teams_workshop_id_workshops_id_fk": {
          "name": "teams_workshop_id_workshops_id_fk",
          "tableFrom": "teams",
          "tableTo": "workshops",
          "columnsFrom": [
            "workshop_id"
          ],
          "columnsTo": [
            "id"
          ],
          "onDelete": "no action",
          "onUpdate": "no action"
        }
      },
      "compositePrimaryKeys": {},
      "uniqueConstraints": {},
      "policies": {},
      "checkConstraints": {},
      "isRLSEnabled": false
    },
    "public.tenants": {
      "name": "tenants",
      "schema": "",
      "columns": {
        "id": {
          "name": "id",
          "type": "text",
          "primaryKey": true,
          "notNull": true
        },
        "name": {
          "name": "name",
          "type": "text",
          "primaryKey": false,
          "notNull": true
        },
        "domain": {
          "name": "domain",
          "type": "text",
          "primaryKey": false,
          "notNull": false
        },
        "created_at": {
          "name": "created_at",
          "type": "timestamp",
          "primaryKey": false,
          "notNull": true,
          "default": "now()"
        }
      },
      "indexes": {},
      "foreignKeys": {},
      "compositePrimaryKeys": {},
      "uniqueConstraints": {},
      "policies": {},
      "checkConstraints": {},
      "isRLSEnabled": false
    },
    "public.use_cases": {
      "name": "use_cases",
      "schema": "",
      "columns": {
        "id": {
          "name": "id",
          "type": "text",
          "primaryKey": true,
          "notNull": true
        },
        "workshop_id": {
          "name": "workshop_id",
          "type": "text",
          "primaryKey": false,
          "notNull": true
        },
        "team_id": {
          "name": "team_id",
          "type": "text",
          "primaryKey": false,
          "notNull": true
        },
        "participant_id": {
          "name": "participant_id",
          "type": "text",
          "primaryKey": false,
          "notNull": true
        },
        "title": {
          "name": "title",
          "type": "text",
          "primaryKey": false,
          "notNull": true
        },
        "summary": {
          "name": "summary",
          "type": "text",
          "primaryKey": false,
          "notNull": true
        },
        "value": {
          "name": "value",
          "type": "text",
          "primaryKey": false,
          "notNull": true
        },
        "viability": {
          "name": "viability",
          "type": "text",
          "primaryKey": false,
          "notNull": true
        },
        "visibility": {
          "name": "visibility",
          "type": "text",
          "primaryKey": false,
          "notNull": true
        },
        "added_by": {
          "name": "added_by",
          "type": "text",
          "primaryKey": false,
          "notNull": true
        },
        "upvotes": {
          "name": "upvotes",
          "type": "integer",
          "primaryKey": false,
          "notNull": true,
          "default": 0
        },
        "upvoted_by": {
          "name": "upvoted_by",
          "type": "jsonb",
          "primaryKey": false,
          "notNull": true,
          "default": "'[]'"
        },
        "comments": {
          "name": "comments",
          "type": "integer",
          "primaryKey": false,
          "notNull": true,
          "default": 0
        },
        "collaborators": {
          "name": "collaborators",
          "type": "jsonb",
          "primaryKey": false,
          "notNull": true,
          "default": "'[]'"
        },
        "cross_team_overlap": {
          "name": "cross_team_overlap",
          "type": "text",
          "primaryKey": false,
          "notNull": false
        },
        "position": {
          "name": "position",
          "type": "jsonb",
          "primaryKey": false,
          "notNull": true,
          "default": "'{\"x\":0,\"y\":0}'"
        },
        "cluster_id": {
          "name": "cluster_id",
          "type": "integer",
          "primaryKey": false,
          "notNull": false
        },
        "why_it_matters": {
          "name": "why_it_matters",
          "type": "text",
          "primaryKey": false,
          "notNull": false
        },
        "created_at": {
          "name": "created_at",
          "type": "timestamp",
          "primaryKey": false,
          "notNull": true,
          "default": "now()"
        }
      },
      "indexes": {},
      "foreignKeys": {
        "use_cases_workshop_id_workshops_id_fk": {
          "name": "use_cases_workshop_id_workshops_id_fk",
          "tableFrom": "use_cases",
          "tableTo": "workshops",
          "columnsFrom": [
            "workshop_id"
          ],
          "columnsTo": [
            "id"
          ],
          "onDelete": "no action",
          "onUpdate": "no action"
        },
        "use_cases_team_id_teams_id_fk": {
          "name": "use_cases_team_id_teams_id_fk",
          "tableFrom": "use_cases",
          "tableTo": "teams",
          "columnsFrom": [
            "team_id"
          ],
          "columnsTo": [
            "id"
          ],
          "onDelete": "no action",
          "onUpdate": "no action"
        },
        "use_cases_participant_id_participants_id_fk": {
          "name": "use_cases_participant_id_participants_id_fk",
          "tableFrom": "use_cases",
          "tableTo": "participants",
          "columnsFrom": [
            "participant_id"
          ],
          "columnsTo": [
            "id"
          ],
          "onDelete": "no action",
          "onUpdate": "no action"
        }
      },
      "compositePrimaryKeys": {},
      "uniqueConstraints": {},
      "policies": {},
      "checkConstraints": {},
      "isRLSEnabled": false
    },
    "public.workshop_summaries": {
      "name": "workshop_summaries",
      "schema": "",
      "columns": {
        "id": {
          "name": "id",
          "type": "text",
          "primaryKey": true,
          "notNull": true
        },
        "workshop_id": {
          "name": "workshop_id",
          "type": "text",
          "primaryKey": false,
          "notNull": true
        },
        "content": {
          "name": "content",
          "type": "jsonb",
          "primaryKey": false,
          "notNull": true
        },
        "generated_at": {
          "name": "generated_at",
          "type": "timestamp",
          "primaryKey": false,
          "notNull": true,
          "default": "now()"
        }
      },
      "indexes": {},
      "foreignKeys": {
        "workshop_summaries_workshop_id_workshops_id_fk": {
          "name": "workshop_summaries_workshop_id_workshops_id_fk",
          "tableFrom": "workshop_summaries",
          "tableTo": "workshops",
          "columnsFrom": [
            "workshop_id"
          ],
          "columnsTo": [
            "id"
          ],
          "onDelete": "no action",
          "onUpdate": "no action"
        }
      },
      "compositePrimaryKeys": {},
      "uniqueConstraints": {},
      "policies": {},
      "checkConstraints": {},
      "isRLSEnabled": false
    },
    "public.workshops": {
      "name": "workshops",
      "schema": "",
      "columns": {
        "id": {
          "name": "id",
          "type": "text",
          "primaryKey": true,
          "notNull": true
        },
        "title": {
          "name": "title",
          "type": "text",
          "primaryKey": false,
          "notNull": true
        },
        "client": {
          "name": "client",
          "type": "text",
          "primaryKey": false,
          "notNull": true
        },
        "status": {
          "name": "status",
          "type": "text",
          "primaryKey": false,
          "notNull": true,
          "default": "'setup'"
        },
        "created_at": {
          "name": "created_at",
          "type": "timestamp",
          "primaryKey": false,
          "notNull": true,
          "default": "now()"
        },
        "agenda": {
          "name": "agenda",
          "type": "jsonb",
          "primaryKey": false,
          "notNull": false
        },
        "objectives": {
          "name": "objectives",
          "type": "jsonb",
          "primaryKey": false,
          "notNull": false,
          "default": "'[]'"
        },
        "strategic_pillars": {
          "name": "strategic_pillars",
          "type": "jsonb",
          "primaryKey": false,
          "notNull": false,
          "default": "'[]'"
        },
        "finished_voting": {
          "name": "finished_voting",
          "type": "jsonb",
          "primaryKey": false,
          "notNull": false,
          "default": "'[]'"
        }
      },
      "indexes": {},
      "foreignKeys": {},
      "compositePrimaryKeys": {},
      "uniqueConstraints": {},
      "policies": {},
      "checkConstraints": {},
      "isRLSEnabled": false
    }
  },
  "enums": {},
  "schemas": {},
  "sequences": {},
  "roles": {},
  "policies": {},
  "views": {},
  "_meta": {
    "columns": {},
    "schemas": {},
    "tables": {}
  }
}